llama_index_tools_praisonai/__init__.py
llama_index_tools_praisonai/tools.py
llama_index_tools_praisonai-0.1.0.dist-info/licenses/LICENSE
llama_index_tools_praisonai-0.1.0.dist-info/METADATA
llama_index_tools_praisonai-0.1.0.dist-info/WHEEL
llama_index_tools_praisonai-0.1.0.dist-info/top_level.txt
llama_index_tools_praisonai-0.1.0.dist-info/RECORD
